factorial_aivn_vc/__init__.py
factorial_aivn_vc/add.py
factorial_aivn_vc/factorial.py
factorial_aivn_vc-0.1.0.dist-info/METADATA
factorial_aivn_vc-0.1.0.dist-info/WHEEL
factorial_aivn_vc-0.1.0.dist-info/RECORD
